[{"id": "573779", "type": "issues", "attributes": {"title": "Stock verification", "description": "<p>A stock take of raw materials, packaging materials, crates and finished products was conducted in Majengo 1 branch on 23rd Jan 2024.\u00a0</p><p>Reconciliation of physical stock and book balances did not reveal any significant variation.</p>", "creator_name": "Julius Langat", "created_at": "2025-01-24T13:05:15Z", "updated_at": "2025-01-24T13:05:15Z", "position": 1, "owner": "Head of operations", "recommendation": "<p>Maintain proper controls as designed</p>", "deficiency_type": "Management Recommendation", "severity": "Low", "published": true, "identified_at": "2025-01-23T00:00:00Z", "reference": null, "reference_prefix": "Inve-001-Con-001", "risk": null, "scope": null, "escalation": null, "cause": "", "effect": "", "cost_impact": null, "executive_summary": null, "executive_owner": null, "project_owner": null, "closed": false, "remediation_status": null, "remediation_plan": null, "remediation_date": null, "actual_remediation_date": null, "retest_deadline_date": null, "actual_retest_date": null, "retesting_results_overview": null, "custom_attributes": [{"id": "20317", "term": "Management  Comments 1", "value": ["<p>Controls will continue to be followed</p>"], "required": false, "default_values": []}, {"id": "20318", "term": "Management Comments 2", "value": ["<p>The trend will be observed</p>"], "required": false, "default_values": []}, {"id": "20319", "term": "Follow-up Findings", "value": ["<p>No variances in inventory items was reported in the previous audit findings</p>"], "required": false, "default_values": []}, {"id": "20488", "term": "Current / Previous finding", "value": ["Current"], "required": false, "default_values": []}, {"id": "20507", "term": "Introduction ", "value": null, "required": false, "default_values": []}, {"id": "20508", "term": "Conclusion", "value": null, "required": false, "default_values": []}, {"id": "20511", "term": "Department", "value": null, "required": false, "default_values": []}, {"id": "20555", "term": "Objectives", "value": null, "required": false, "default_values": []}]}, "relationships": {"project": {"data": {"id": "125267", "type": "projects"}}, "owner_user": {"data": null}, "executive_owner_user": {"data": null}, "project_owner_user": {"data": null}, "creator_user": {"data": {"id": "QH8FDeMD3W6pjsdr-Dsi", "type": "users"}}}}, {"id": "573835", "type": "issues", "attributes": {"title": "Cash verification", "description": "<p>Physical cash verification of cash at hand as compared to book (SAP system) balances.</p>", "creator_name": "Benard Kioko", "created_at": "2025-01-25T09:09:27Z", "updated_at": "2025-01-25T09:51:29Z", "position": 2, "owner": "Head of finance department", "recommendation": "<p>Minimal variance shows that set controls were effecti<i>ve.</i></p>", "deficiency_type": "Management Recommendation", "severity": "Low", "published": true, "identified_at": "2025-01-23T00:00:00Z", "reference": null, "reference_prefix": "CV-002", "risk": null, "scope": null, "escalation": null, "cause": "", "effect": "", "cost_impact": null, "executive_summary": null, "executive_owner": null, "project_owner": null, "closed": false, "remediation_status": null, "remediation_plan": null, "remediation_date": null, "actual_remediation_date": null, "retest_deadline_date": null, "actual_retest_date": null, "retesting_results_overview": null, "custom_attributes": [{"id": "20317", "term": "Management  Comments 1", "value": ["<p>Cash verification is done on weekly basis to ensure minimal variances.</p>"], "required": false, "default_values": []}, {"id": "20318", "term": "Management Comments 2", "value": ["<p>- Regular cash verification is conducted to address cash shortfalls/surpluses.</p>"], "required": false, "default_values": []}, {"id": "20319", "term": "Follow-up Findings", "value": ["<p>None.</p>"], "required": false, "default_values": []}, {"id": "20488", "term": "Current / Previous finding", "value": ["Current"], "required": false, "default_values": []}, {"id": "20507", "term": "Introduction ", "value": ["<p>Physical cash count is done to determine if there are variations with the book/SAP system balances.</p>"], "required": false, "default_values": []}, {"id": "20508", "term": "Conclusion", "value": ["<p>&nbsp;Accountability of cash was noted.</p>"], "required": false, "default_values": []}, {"id": "20511", "term": "Department", "value": ["Finance Department"], "required": false, "default_values": []}, {"id": "20555", "term": "Objectives", "value": ["<p>- To ensure that all cash collected was fully accounted for.</p>"], "required": false, "default_values": []}]}, "relationships": {"project": {"data": {"id": "125267", "type": "projects"}}, "owner_user": {"data": null}, "executive_owner_user": {"data": null}, "project_owner_user": {"data": null}, "creator_user": {"data": {"id": "Km8zMn-Uco1u-KvzsRhj", "type": "users"}}}}, {"id": "573840", "type": "issues", "attributes": {"title": "Bread Weight Control & Compliance", "description": "<p>Minimal cases of underweight and overweight breads.</p>", "creator_name": "Maurice Thuku", "created_at": "2025-01-25T10:21:13Z", "updated_at": "2025-02-03T15:44:37Z", "position": 3, "owner": "Head of Operations", "recommendation": "<p><span style='font-family:\"Times New Roman\",\"serif\";font-size:12.0pt;'><span style=\"\">Strict adherence to established weight standards for bread production to help maintain consistency in product quality and prevent discrepancies in weights.</span></span></p>", "deficiency_type": "Management Recommendation", "severity": "Low", "published": true, "identified_at": "2025-01-25T10:08:39Z", "reference": null, "reference_prefix": null, "risk": null, "scope": null, "escalation": null, "cause": "", "effect": "", "cost_impact": null, "executive_summary": null, "executive_owner": null, "project_owner": null, "closed": false, "remediation_status": null, "remediation_plan": null, "remediation_date": null, "actual_remediation_date": null, "retest_deadline_date": null, "actual_retest_date": null, "retesting_results_overview": null, "custom_attributes": [{"id": "20317", "term": "Management  Comments 1", "value": null, "required": false, "default_values": []}, {"id": "20318", "term": "Management Comments 2", "value": null, "required": false, "default_values": []}, {"id": "20319", "term": "Follow-up Findings", "value": ["<p><span style=\"color:black;font-family:&quot;Times New Roman&quot;,&quot;serif&quot;;font-size:12.0pt;\"><span style=\"layout-grid-mode:line;mso-ansi-language:EN-GB;mso-bidi-language:AR-SA;mso-fareast-font-family:&quot;Times New Roman&quot;;mso-fareast-language:EN-GB;\" lang=\"EN-GB\" dir=\"ltr\">More effort will be in place to minimize the percentage noted in that period of audit.</span></span></p>"], "required": false, "default_values": []}, {"id": "20488", "term": "Current / Previous finding", "value": ["Current"], "required": false, "default_values": []}, {"id": "20507", "term": "Introduction ", "value": null, "required": false, "default_values": []}, {"id": "20508", "term": "Conclusion", "value": null, "required": false, "default_values": []}, {"id": "20511", "term": "Department", "value": ["Operations/Production Department"], "required": false, "default_values": []}, {"id": "20555", "term": "Objectives", "value": null, "required": false, "default_values": []}]}, "relationships": {"project": {"data": {"id": "125267", "type": "projects"}}, "owner_user": {"data": null}, "executive_owner_user": {"data": null}, "project_owner_user": {"data": null}, "creator_user": {"data": {"id": "28tEVYq2cwDXk8HzLRAV", "type": "users"}}}}, {"id": "575780", "type": "issues", "attributes": {"title": "Automated BOM", "description": "<p>BOM is automated at the branch.</p>", "creator_name": "Benard Kioko", "created_at": "2025-02-03T15:45:15Z", "updated_at": "2025-02-03T15:45:15Z", "position": 4, "owner": "Head of Operations", "recommendation": "<p>Set BOM was adhered to.</p>", "deficiency_type": "Management Recommendation", "severity": "Low", "published": true, "identified_at": "2025-02-03T15:35:26Z", "reference": null, "reference_prefix": "01-01", "risk": null, "scope": null, "escalation": null, "cause": "", "effect": "", "cost_impact": null, "executive_summary": null, "executive_owner": null, "project_owner": null, "closed": false, "remediation_status": null, "remediation_plan": null, "remediation_date": null, "actual_remediation_date": null, "retest_deadline_date": null, "actual_retest_date": null, "retesting_results_overview": null, "custom_attributes": [{"id": "20317", "term": "Management  Comments 1", "value": ["<p>Set BOMs at the branch is always followed.</p>"], "required": false, "default_values": []}, {"id": "20318", "term": "Management Comments 2", "value": ["<p>Set BOMs at the branch is always followed.</p>"], "required": false, "default_values": []}, {"id": "20319", "term": "Follow-up Findings", "value": null, "required": false, "default_values": []}, {"id": "20488", "term": "Current / Previous finding", "value": ["Current"], "required": false, "default_values": []}, {"id": "20507", "term": "Introduction ", "value": null, "required": false, "default_values": []}, {"id": "20508", "term": "Conclusion", "value": null, "required": false, "default_values": []}, {"id": "20511", "term": "Department", "value": null, "required": false, "default_values": []}, {"id": "20555", "term": "Objectives", "value": null, "required": false, "default_values": []}]}, "relationships": {"project": {"data": {"id": "125267", "type": "projects"}}, "owner_user": {"data": null}, "executive_owner_user": {"data": null}, "project_owner_user": {"data": null}, "creator_user": {"data": {"id": "Km8zMn-Uco1u-KvzsRhj", "type": "users"}}}}, {"id": "575781", "type": "issues", "attributes": {"title": "Mixing chart verification", "description": "<p>Spot check on mixing chart for ongoing production showed that it was well updated and mixing chart recorded quantities matched those physically counted.</p>", "creator_name": "Benard Kioko", "created_at": "2025-02-03T15:59:37Z", "updated_at": "2025-02-03T15:59:37Z", "position": 5, "owner": "Head of operations", "recommendation": "<p>Noted real time updating of mixing charts is commendable.</p>", "deficiency_type": "Management Recommendation", "severity": "Low", "published": true, "identified_at": "2025-02-03T15:50:55Z", "reference": null, "reference_prefix": "01-02", "risk": null, "scope": null, "escalation": null, "cause": "", "effect": "", "cost_impact": null, "executive_summary": null, "executive_owner": null, "project_owner": null, "closed": false, "remediation_status": null, "remediation_plan": null, "remediation_date": null, "actual_remediation_date": null, "retest_deadline_date": null, "actual_retest_date": null, "retesting_results_overview": null, "custom_attributes": [{"id": "20317", "term": "Management  Comments 1", "value": ["<p>We always conduct spot checks to ensure mixing charts are properly updated.</p><p>&nbsp;</p>"], "required": false, "default_values": []}, {"id": "20318", "term": "Management Comments 2", "value": ["<p>- Dough dividers are always sensitized on updating mixing charts real time to ensure compliance. Foremen are always directed to confirm mixing charts records during production and countersign against all confirmed mixes.</p>"], "required": false, "default_values": []}, {"id": "20319", "term": "Follow-up Findings", "value": null, "required": false, "default_values": []}, {"id": "20488", "term": "Current / Previous finding", "value": null, "required": false, "default_values": []}, {"id": "20507", "term": "Introduction ", "value": null, "required": false, "default_values": []}, {"id": "20508", "term": "Conclusion", "value": null, "required": false, "default_values": []}, {"id": "20511", "term": "Department", "value": null, "required": false, "default_values": []}, {"id": "20555", "term": "Objectives", "value": null, "required": false, "default_values": []}]}, "relationships": {"project": {"data": {"id": "125267", "type": "projects"}}, "owner_user": {"data": null}, "executive_owner_user": {"data": null}, "project_owner_user": {"data": null}, "creator_user": {"data": {"id": "Km8zMn-Uco1u-KvzsRhj", "type": "users"}}}}, {"id": "575787", "type": "issues", "attributes": {"title": "Physical stock verification.", "description": "<p>- Physical stock counted for raw materials, packing materials and finished goods showed insignificant variation when compared to SAP balances.</p><p>Crates counted also matched quantities indicated on SAP system.</p><p>\u00a0</p>", "creator_name": "Benard Kioko", "created_at": "2025-02-03T16:23:44Z", "updated_at": "2025-02-03T16:23:44Z", "position": 6, "owner": "Head of Operations", "recommendation": "<p>Strong internal controls were noted.</p>", "deficiency_type": "Management Recommendation", "severity": "Low", "published": true, "identified_at": "2025-02-03T16:14:37Z", "reference": null, "reference_prefix": "01-03", "risk": null, "scope": null, "escalation": null, "cause": "", "effect": "", "cost_impact": null, "executive_summary": null, "executive_owner": null, "project_owner": null, "closed": false, "remediation_status": null, "remediation_plan": null, "remediation_date": null, "actual_remediation_date": null, "retest_deadline_date": null, "actual_retest_date": null, "retesting_results_overview": null, "custom_attributes": [{"id": "20317", "term": "Management  Comments 1", "value": ["<p>- Physical stock is conducted on daily basis to ensure no item loss.</p>"], "required": false, "default_values": []}, {"id": "20318", "term": "Management Comments 2", "value": ["<p>- Weekly stock take is normally done and any significant variance addressed.</p>"], "required": false, "default_values": []}, {"id": "20319", "term": "Follow-up Findings", "value": null, "required": false, "default_values": []}, {"id": "20488", "term": "Current / Previous finding", "value": null, "required": false, "default_values": []}, {"id": "20507", "term": "Introduction ", "value": null, "required": false, "default_values": []}, {"id": "20508", "term": "Conclusion", "value": null, "required": false, "default_values": []}, {"id": "20511", "term": "Department", "value": null, "required": false, "default_values": []}, {"id": "20555", "term": "Objectives", "value": null, "required": false, "default_values": []}]}, "relationships": {"project": {"data": {"id": "125267", "type": "projects"}}, "owner_user": {"data": null}, "executive_owner_user": {"data": null}, "project_owner_user": {"data": null}, "creator_user": {"data": {"id": "Km8zMn-Uco1u-KvzsRhj", "type": "users"}}}}, {"id": "575790", "type": "issues", "attributes": {"title": "Raw and packing material records", "description": "<p>Foreman's raw material register was verified and it was noted that the register was well updated with the quantities matching those of SAP system.</p><p>Branch managers bread balance register was also properly updated.\u00a0</p>", "creator_name": "Benard Kioko", "created_at": "2025-02-03T16:34:53Z", "updated_at": "2025-02-03T16:34:53Z", "position": 7, "owner": "Head of Operations", "recommendation": "<p>- Raw and packing materials registers together with bread balance register were well maintained.</p>", "deficiency_type": "Management Recommendation", "severity": "Low", "published": true, "identified_at": "2025-02-03T16:27:05Z", "reference": null, "reference_prefix": "01-03", "risk": null, "scope": null, "escalation": null, "cause": "", "effect": "", "cost_impact": null, "executive_summary": null, "executive_owner": null, "project_owner": null, "closed": false, "remediation_status": null, "remediation_plan": null, "remediation_date": null, "actual_remediation_date": null, "retest_deadline_date": null, "actual_retest_date": null, "retesting_results_overview": null, "custom_attributes": [{"id": "20317", "term": "Management  Comments 1", "value": ["<p>- Raw materials register is daily updated.</p><p>- Bread balance register is always updated real time.</p>"], "required": false, "default_values": []}, {"id": "20318", "term": "Management Comments 2", "value": ["<p>- Registers are regularly verified to ensure compliance.</p>"], "required": false, "default_values": []}, {"id": "20319", "term": "Follow-up Findings", "value": null, "required": false, "default_values": []}, {"id": "20488", "term": "Current / Previous finding", "value": null, "required": false, "default_values": []}, {"id": "20507", "term": "Introduction ", "value": null, "required": false, "default_values": []}, {"id": "20508", "term": "Conclusion", "value": null, "required": false, "default_values": []}, {"id": "20511", "term": "Department", "value": null, "required": false, "default_values": []}, {"id": "20555", "term": "Objectives", "value": null, "required": false, "default_values": []}]}, "relationships": {"project": {"data": {"id": "125267", "type": "projects"}}, "owner_user": {"data": null}, "executive_owner_user": {"data": null}, "project_owner_user": {"data": null}, "creator_user": {"data": {"id": "Km8zMn-Uco1u-KvzsRhj", "type": "users"}}}}, {"id": "575791", "type": "issues", "attributes": {"title": "Stock take register maintenance", "description": "<p>- Verification of stock take registers showed that foremen and managers did daily stock take while the operations manager di a weekly stock take and registers were properly maintained.</p>", "creator_name": "Benard Kioko", "created_at": "2025-02-03T16:44:11Z", "updated_at": "2025-02-03T16:44:12Z", "position": 8, "owner": "Head of Operations", "recommendation": "<p>- Stock take registers were properly maintained.</p>", "deficiency_type": "Management Recommendation", "severity": "Low", "published": true, "identified_at": "2025-02-03T16:39:00Z", "reference": null, "reference_prefix": "01-04", "risk": null, "scope": null, "escalation": null, "cause": "", "effect": "", "cost_impact": null, "executive_summary": null, "executive_owner": null, "project_owner": null, "closed": false, "remediation_status": null, "remediation_plan": null, "remediation_date": null, "actual_remediation_date": null, "retest_deadline_date": null, "actual_retest_date": null, "retesting_results_overview": null, "custom_attributes": [{"id": "20317", "term": "Management  Comments 1", "value": ["<p>- Stock taking is done daily and stock books updated.</p>"], "required": false, "default_values": []}, {"id": "20318", "term": "Management Comments 2", "value": ["<p>- Registers are properly maintained.</p>"], "required": false, "default_values": []}, {"id": "20319", "term": "Follow-up Findings", "value": null, "required": false, "default_values": []}, {"id": "20488", "term": "Current / Previous finding", "value": null, "required": false, "default_values": []}, {"id": "20507", "term": "Introduction ", "value": null, "required": false, "default_values": []}, {"id": "20508", "term": "Conclusion", "value": null, "required": false, "default_values": []}, {"id": "20511", "term": "Department", "value": null, "required": false, "default_values": []}, {"id": "20555", "term": "Objectives", "value": null, "required": false, "default_values": []}]}, "relationships": {"project": {"data": {"id": "125267", "type": "projects"}}, "owner_user": {"data": null}, "executive_owner_user": {"data": null}, "project_owner_user": {"data": null}, "creator_user": {"data": {"id": "Km8zMn-Uco1u-KvzsRhj", "type": "users"}}}}, {"id": "575901", "type": "issues", "attributes": {"title": "Raw materials weights spot checks", "description": "<p>- Flour, ingredients and utto were picked randomly and weighed on 23/01/2025.\u00a0</p><p>- Resulting individual weights were then recorded and compared to set standard weights.</p><p>- Random weights tested showed that they conformed to set standards (weights were within the expected standards).\u00a0</p>", "creator_name": "Benard Kioko", "created_at": "2025-02-04T11:19:07Z", "updated_at": "2025-02-04T11:19:07Z", "position": 9, "owner": "Regional Operations Manager", "recommendation": "<p>- Raw materials weights adherence to set standards is commendable and the trend should be maintained.</p>", "deficiency_type": "Management Recommendation", "severity": "Low", "published": true, "identified_at": "2025-02-04T11:10:53Z", "reference": null, "reference_prefix": "02-01", "risk": null, "scope": null, "escalation": null, "cause": "", "effect": "", "cost_impact": null, "executive_summary": null, "executive_owner": null, "project_owner": null, "closed": false, "remediation_status": null, "remediation_plan": null, "remediation_date": null, "actual_remediation_date": null, "retest_deadline_date": null, "actual_retest_date": null, "retesting_results_overview": null, "custom_attributes": [{"id": "20317", "term": "Management  Comments 1", "value": ["<p>- We normally randomly take sample weights upon receiving raw materials at the branch and escalate incase of non-compliance.</p>"], "required": false, "default_values": []}, {"id": "20318", "term": "Management Comments 2", "value": ["<p>- Noted trend will be maintained.</p>"], "required": false, "default_values": []}, {"id": "20319", "term": "Follow-up Findings", "value": null, "required": false, "default_values": []}, {"id": "20488", "term": "Current / Previous finding", "value": null, "required": false, "default_values": []}, {"id": "20507", "term": "Introduction ", "value": null, "required": false, "default_values": []}, {"id": "20508", "term": "Conclusion", "value": null, "required": false, "default_values": []}, {"id": "20511", "term": "Department", "value": null, "required": false, "default_values": []}, {"id": "20555", "term": "Objectives", "value": null, "required": false, "default_values": []}]}, "relationships": {"project": {"data": {"id": "125267", "type": "projects"}}, "owner_user": {"data": null}, "executive_owner_user": {"data": null}, "project_owner_user": {"data": null}, "creator_user": {"data": {"id": "Km8zMn-Uco1u-KvzsRhj", "type": "users"}}}}, {"id": "575904", "type": "issues", "attributes": {"title": "Dough weights", "description": "<p>- Dough weights were sampled on 23.01.2025 for both 200g white and 400g white bread for ongoing production.</p><p>- Weights sampled showed that over and underweight samples were minimal when compared to set dough dividing standard weights.</p>", "creator_name": "Benard Kioko", "created_at": "2025-02-04T11:27:47Z", "updated_at": "2025-02-04T11:27:48Z", "position": 10, "owner": "Regional Operations Manager", "recommendation": "<p>- Dough weights compliance was noted which is commendable.</p>", "deficiency_type": "Management Recommendation", "severity": "Medium", "published": true, "identified_at": "2025-02-04T11:20:52Z", "reference": null, "reference_prefix": "02-02", "risk": null, "scope": null, "escalation": null, "cause": "", "effect": "", "cost_impact": null, "executive_summary": null, "executive_owner": null, "project_owner": null, "closed": false, "remediation_status": null, "remediation_plan": null, "remediation_date": null, "actual_remediation_date": null, "retest_deadline_date": null, "actual_retest_date": null, "retesting_results_overview": null, "custom_attributes": [{"id": "20317", "term": "Management  Comments 1", "value": ["<p>- We always sensitize dough dividers to adhere to set dividing weights.</p><p>- We will always ensure compliance.</p>"], "required": false, "default_values": []}, {"id": "20318", "term": "Management Comments 2", "value": null, "required": false, "default_values": []}, {"id": "20319", "term": "Follow-up Findings", "value": ["<p>- Production of required standard weight bread is a priority and we always monitor dough dividing weights to ensure compliance.</p>"], "required": false, "default_values": []}, {"id": "20488", "term": "Current / Previous finding", "value": null, "required": false, "default_values": []}, {"id": "20507", "term": "Introduction ", "value": null, "required": false, "default_values": []}, {"id": "20508", "term": "Conclusion", "value": null, "required": false, "default_values": []}, {"id": "20511", "term": "Department", "value": null, "required": false, "default_values": []}, {"id": "20555", "term": "Objectives", "value": null, "required": false, "default_values": []}]}, "relationships": {"project": {"data": {"id": "125267", "type": "projects"}}, "owner_user": {"data": null}, "executive_owner_user": {"data": null}, "project_owner_user": {"data": null}, "creator_user": {"data": {"id": "Km8zMn-Uco1u-KvzsRhj", "type": "users"}}}}, {"id": "575909", "type": "issues", "attributes": {"title": "Preventive maintenance schedule.", "description": "<p>- Preventive maintenance schedule was seen pinned on noticeboard. Worksheet copies for preventive maintenance done were also properly filed.</p><p>- Timely maintenance plan was noted.</p>", "creator_name": "Benard Kioko", "created_at": "2025-02-04T11:37:10Z", "updated_at": "2025-02-04T11:37:10Z", "position": 11, "owner": "Regional Operations Manager", "recommendation": "<p>- Adherence to preventive maintenance schedule is commendable and the trend should be maintained.</p>", "deficiency_type": "Management Recommendation", "severity": "Medium", "published": true, "identified_at": "2025-02-04T11:29:48Z", "reference": null, "reference_prefix": "02-03", "risk": null, "scope": null, "escalation": null, "cause": "", "effect": "", "cost_impact": null, "executive_summary": null, "executive_owner": null, "project_owner": null, "closed": false, "remediation_status": null, "remediation_plan": null, "remediation_date": null, "actual_remediation_date": null, "retest_deadline_date": null, "actual_retest_date": null, "retesting_results_overview": null, "custom_attributes": [{"id": "20317", "term": "Management  Comments 1", "value": ["<p>- We always ensure that machines are serviced within the planned time frame.</p>"], "required": false, "default_values": []}, {"id": "20318", "term": "Management Comments 2", "value": ["<p>- Noted trend will be maintained.</p>"], "required": false, "default_values": []}, {"id": "20319", "term": "Follow-up Findings", "value": null, "required": false, "default_values": []}, {"id": "20488", "term": "Current / Previous finding", "value": null, "required": false, "default_values": []}, {"id": "20507", "term": "Introduction ", "value": null, "required": false, "default_values": []}, {"id": "20508", "term": "Conclusion", "value": null, "required": false, "default_values": []}, {"id": "20511", "term": "Department", "value": null, "required": false, "default_values": []}, {"id": "20555", "term": "Objectives", "value": null, "required": false, "default_values": []}]}, "relationships": {"project": {"data": {"id": "125267", "type": "projects"}}, "owner_user": {"data": null}, "executive_owner_user": {"data": null}, "project_owner_user": {"data": null}, "creator_user": {"data": {"id": "Km8zMn-Uco1u-KvzsRhj", "type": "users"}}}}, {"id": "575918", "type": "issues", "attributes": {"title": "Packing Efficiency", "description": "<p>When packing efficiency is optimized, the company is more likely to meet daily or weekly production targets, reducing the risk of falling behind in fulfilling orders and avoiding disruptions in the supply chain.</p>", "creator_name": "Maurice Thuku", "created_at": "2025-02-04T11:56:39Z", "updated_at": "2025-02-04T11:56:39Z", "position": 12, "owner": "Maurice Thuku", "recommendation": "<p>The packing efficiency should be achieved on daily basis.\u00a0</p>", "deficiency_type": "Management Recommendation", "severity": "Low", "published": true, "identified_at": "2025-02-04T11:04:05Z", "reference": null, "reference_prefix": "12", "risk": null, "scope": null, "escalation": null, "cause": "", "effect": "", "cost_impact": null, "executive_summary": null, "executive_owner": null, "project_owner": null, "closed": false, "remediation_status": null, "remediation_plan": null, "remediation_date": null, "actual_remediation_date": null, "retest_deadline_date": null, "actual_retest_date": null, "retesting_results_overview": null, "custom_attributes": [{"id": "20317", "term": "Management  Comments 1", "value": null, "required": false, "default_values": []}, {"id": "20318", "term": "Management Comments 2", "value": null, "required": false, "default_values": []}, {"id": "20319", "term": "Follow-up Findings", "value": [], "required": false, "default_values": []}, {"id": "20488", "term": "Current / Previous finding", "value": ["Current"], "required": false, "default_values": []}, {"id": "20507", "term": "Introduction ", "value": ["<p>Efficient packing helps ensure that bread is packed and ready for delivery on time.</p>"], "required": false, "default_values": []}, {"id": "20508", "term": "Conclusion", "value": ["<p>The target efficiency was achieved.</p>"], "required": false, "default_values": []}, {"id": "20511", "term": "Department", "value": ["Operations/Production Department"], "required": false, "default_values": []}, {"id": "20555", "term": "Objectives", "value": ["<p>To ensure each packer achieves his or her efficiency.</p>"], "required": false, "default_values": []}]}, "relationships": {"project": {"data": {"id": "125267", "type": "projects"}}, "owner_user": {"data": {"id": "28tEVYq2cwDXk8HzLRAV", "type": "users"}}, "executive_owner_user": {"data": null}, "project_owner_user": {"data": null}, "creator_user": {"data": {"id": "28tEVYq2cwDXk8HzLRAV", "type": "users"}}}}, {"id": "575936", "type": "issues", "attributes": {"title": "Presence of cashless system", "description": "<p>Use of Mpesa system to collect sales revenues</p>", "creator_name": "Julius Langat", "created_at": "2025-02-04T12:30:22Z", "updated_at": "2025-02-04T12:30:22Z", "position": 13, "owner": "Head of finance", "recommendation": "<p>Good system to be maintained</p>", "deficiency_type": "Management Recommendation", "severity": "Low", "published": true, "identified_at": "2025-01-23T00:00:00Z", "reference": null, "reference_prefix": "07-01", "risk": null, "scope": null, "escalation": null, "cause": "", "effect": "", "cost_impact": null, "executive_summary": null, "executive_owner": null, "project_owner": null, "closed": false, "remediation_status": null, "remediation_plan": null, "remediation_date": null, "actual_remediation_date": null, "retest_deadline_date": null, "actual_retest_date": null, "retesting_results_overview": null, "custom_attributes": [{"id": "20317", "term": "Management  Comments 1", "value": ["<p>The trend will be maintained</p>"], "required": false, "default_values": []}, {"id": "20318", "term": "Management Comments 2", "value": ["<p>To be maintained</p>"], "required": false, "default_values": []}, {"id": "20319", "term": "Follow-up Findings", "value": ["<p>No previous audit findings</p>"], "required": false, "default_values": []}, {"id": "20488", "term": "Current / Previous finding", "value": null, "required": false, "default_values": []}, {"id": "20507", "term": "Introduction ", "value": null, "required": false, "default_values": []}, {"id": "20508", "term": "Conclusion", "value": null, "required": false, "default_values": []}, {"id": "20511", "term": "Department", "value": ["Finance Department"], "required": false, "default_values": []}, {"id": "20555", "term": "Objectives", "value": null, "required": false, "default_values": []}]}, "relationships": {"project": {"data": {"id": "125267", "type": "projects"}}, "owner_user": {"data": null}, "executive_owner_user": {"data": null}, "project_owner_user": {"data": null}, "creator_user": {"data": {"id": "QH8FDeMD3W6pjsdr-Dsi", "type": "users"}}}}, {"id": "575938", "type": "issues", "attributes": {"title": "Regular banking of cash", "description": "<p>All cash was regularly banked</p>", "creator_name": "Julius Langat", "created_at": "2025-02-04T12:33:32Z", "updated_at": "2025-02-04T12:33:32Z", "position": 14, "owner": "Head of finance", "recommendation": "<p>-Maintain the good controls</p>", "deficiency_type": "Management Recommendation", "severity": "Low", "published": true, "identified_at": "2025-01-23T00:00:00Z", "reference": null, "reference_prefix": "07-02", "risk": null, "scope": null, "escalation": null, "cause": "", "effect": "", "cost_impact": null, "executive_summary": null, "executive_owner": null, "project_owner": null, "closed": false, "remediation_status": null, "remediation_plan": null, "remediation_date": null, "actual_remediation_date": null, "retest_deadline_date": null, "actual_retest_date": null, "retesting_results_overview": null, "custom_attributes": [{"id": "20317", "term": "Management  Comments 1", "value": ["<p>To be maintained</p>"], "required": false, "default_values": []}, {"id": "20318", "term": "Management Comments 2", "value": ["<p>To be maintained</p>"], "required": false, "default_values": []}, {"id": "20319", "term": "Follow-up Findings", "value": ["<p>No previous audit findings</p>"], "required": false, "default_values": []}, {"id": "20488", "term": "Current / Previous finding", "value": null, "required": false, "default_values": []}, {"id": "20507", "term": "Introduction ", "value": null, "required": false, "default_values": []}, {"id": "20508", "term": "Conclusion", "value": null, "required": false, "default_values": []}, {"id": "20511", "term": "Department", "value": null, "required": false, "default_values": []}, {"id": "20555", "term": "Objectives", "value": null, "required": false, "default_values": []}]}, "relationships": {"project": {"data": {"id": "125267", "type": "projects"}}, "owner_user": {"data": null}, "executive_owner_user": {"data": null}, "project_owner_user": {"data": null}, "creator_user": {"data": {"id": "QH8FDeMD3W6pjsdr-Dsi", "type": "users"}}}}, {"id": "575941", "type": "issues", "attributes": {"title": "Proper documentation of cash records", "description": "<p>-Test perform to verify if proper cash records were maintained</p>", "creator_name": "Julius Langat", "created_at": "2025-02-04T12:37:30Z", "updated_at": "2025-02-04T12:37:30Z", "position": 15, "owner": "Head of finance", "recommendation": "<p>To be maintained</p>", "deficiency_type": "Management Recommendation", "severity": "Low", "published": true, "identified_at": "2025-02-04T12:36:40Z", "reference": null, "reference_prefix": "07-03", "risk": null, "scope": null, "escalation": null, "cause": "", "effect": "", "cost_impact": null, "executive_summary": null, "executive_owner": null, "project_owner": null, "closed": false, "remediation_status": null, "remediation_plan": null, "remediation_date": null, "actual_remediation_date": null, "retest_deadline_date": null, "actual_retest_date": null, "retesting_results_overview": null, "custom_attributes": [{"id": "20317", "term": "Management  Comments 1", "value": ["<p>To be maintained</p>"], "required": false, "default_values": []}, {"id": "20318", "term": "Management Comments 2", "value": ["<p>To be maintained</p>"], "required": false, "default_values": []}, {"id": "20319", "term": "Follow-up Findings", "value": ["<p>No previous audit findings</p>"], "required": false, "default_values": []}, {"id": "20488", "term": "Current / Previous finding", "value": null, "required": false, "default_values": []}, {"id": "20507", "term": "Introduction ", "value": null, "required": false, "default_values": []}, {"id": "20508", "term": "Conclusion", "value": null, "required": false, "default_values": []}, {"id": "20511", "term": "Department", "value": null, "required": false, "default_values": []}, {"id": "20555", "term": "Objectives", "value": null, "required": false, "default_values": []}]}, "relationships": {"project": {"data": {"id": "125267", "type": "projects"}}, "owner_user": {"data": null}, "executive_owner_user": {"data": null}, "project_owner_user": {"data": null}, "creator_user": {"data": {"id": "QH8FDeMD3W6pjsdr-Dsi", "type": "users"}}}}]